Metadata-Version: 2.1
Name: gen-invoices
Version: 1.0.0
Summary: Easily convert Excel invoices into professional PDF formatted invoices, with this Python package, streamlining your invoicing workflow.
Home-page: https://github.com/Aaliyah1699
Author: Aaliyah Montgomery
Author-email: adestanym@gmail.com
License: MIT
Keywords: invoice,excel,pdf
Platform: UNKNOWN
Classifier: Development Status :: 3 - Alpha
Classifier: Intended Audience :: Developers
Classifier: Topic :: Software Development :: Build Tools
Classifier: License :: OSI Approved :: MIT License
Classifier: Programming Language :: Python :: 3.8
Classifier: Programming Language :: Python :: 3.9
Classifier: Programming Language :: Python :: 3.10
Classifier: Programming Language :: Python :: 3.11
